{
  "data": {
    "article": {},
    "attachments": {
      "media_keys": [
        "3_1989702671310417920"
      ],
      "media_source_tweet_id": [
        "1989702678788579781"
      ]
    },
    "author_id": "1511572100225462281",
    "conversation_id": "1989724759400329290",
    "created_at": "2025-11-15T15:58:44.000Z",
    "edit_controls": {
      "editable_until": "2025-11-15T16:58:44.000Z",
      "edits_remaining": 5,
      "is_edit_eligible": false
    },
    "edit_history_tweet_ids": [
      "1989724759400329290"
    ],
    "entities": {
      "mentions": [
        {
          "end": 9,
          "id": "1507396901594820608",
          "start": 3,
          "username": "hgds0"
        }
      ],
      "urls": [
        {
          "display_url": "pic.x.com/0MZ1REvCle",
          "end": 34,
          "expanded_url": "https://x.com/hgds0/status/1989702678788579781/photo/1",
          "media_key": "3_1989702671310417920",
          "start": 11,
          "url": "https://t.co/0MZ1REvCle"
        }
      ]
    },
    "geo": {},
    "id": "1989724759400329290",
    "lang": "zxx",
    "note_tweet": {
      "entities": {}
    },
    "possibly_sensitive": false,
    "public_metrics": {
      "bookmark_count": 0,
      "impression_count": 0,
      "like_count": 0,
      "quote_count": 0,
      "reply_count": 0,
      "retweet_count": 14
    },
    "referenced_tweets": [
      {
        "id": "1989702678788579781",
        "type": "retweeted"
      }
    ],
    "reply_settings": "everyone",
    "text": "RT @hgds0: https://t.co/0MZ1REvCle"
  },
  "includes": {
    "media": [
      {
        "height": 666,
        "media_key": "3_1989702671310417920",
        "public_metrics": {},
        "type": "photo",
        "url": "https://pbs.twimg.com/media/G5zYCaQacAANiJI.jpg",
        "width": 640
      }
    ],
    "tweets": [
      {
        "article": {},
        "attachments": {
          "media_keys": [
            "3_1989702671310417920"
          ],
          "media_source_tweet_id": [
            "1989702678788579781"
          ]
        },
        "author_id": "1511572100225462281",
        "conversation_id": "1989724759400329290",
        "created_at": "2025-11-15T15:58:44.000Z",
        "edit_controls": {
          "editable_until": "2025-11-15T16:58:44.000Z",
          "edits_remaining": 5,
          "is_edit_eligible": false
        },
        "edit_history_tweet_ids": [
          "1989724759400329290"
        ],
        "entities": {
          "mentions": [
            {
              "end": 9,
              "id": "1507396901594820608",
              "start": 3,
              "username": "hgds0"
            }
          ],
          "urls": [
            {
              "display_url": "pic.x.com/0MZ1REvCle",
              "end": 34,
              "expanded_url": "https://x.com/hgds0/status/1989702678788579781/photo/1",
              "media_key": "3_1989702671310417920",
              "start": 11,
              "url": "https://t.co/0MZ1REvCle"
            }
          ]
        },
        "geo": {},
        "id": "1989724759400329290",
        "lang": "zxx",
        "note_tweet": {
          "entities": {}
        },
        "possibly_sensitive": false,
        "public_metrics": {
          "bookmark_count": 0,
          "impression_count": 0,
          "like_count": 0,
          "quote_count": 0,
          "reply_count": 0,
          "retweet_count": 14
        },
        "referenced_tweets": [
          {
            "id": "1989702678788579781",
            "type": "retweeted"
          }
        ],
        "reply_settings": "everyone",
        "text": "RT @hgds0: https://t.co/0MZ1REvCle"
      },
      {
        "article": {},
        "attachments": {
          "media_keys": [
            "3_1989702671310417920"
          ]
        },
        "author_id": "1507396901594820608",
        "conversation_id": "1989702678788579781",
        "created_at": "2025-11-15T14:31:00.000Z",
        "edit_controls": {
          "editable_until": "2025-11-15T15:31:00.000Z",
          "edits_remaining": 5,
          "is_edit_eligible": true
        },
        "edit_history_tweet_ids": [
          "1989702678788579781"
        ],
        "entities": {
          "urls": [
            {
              "display_url": "pic.x.com/0MZ1REvCle",
              "end": 23,
              "expanded_url": "https://x.com/hgds0/status/1989702678788579781/photo/1",
              "media_key": "3_1989702671310417920",
              "start": 0,
              "url": "https://t.co/0MZ1REvCle"
            }
          ]
        },
        "geo": {},
        "id": "1989702678788579781",
        "lang": "zxx",
        "note_tweet": {
          "entities": {}
        },
        "possibly_sensitive": false,
        "public_metrics": {
          "bookmark_count": 4,
          "impression_count": 2659,
          "like_count": 84,
          "quote_count": 1,
          "reply_count": 3,
          "retweet_count": 14
        },
        "reply_settings": "everyone",
        "text": "https://t.co/0MZ1REvCle"
      }
    ],
    "users": [
      {
        "created_at": "2022-04-06T05:11:05.000Z",
        "description": "_未確診的性成癮患者自述 *墮落的自救者**_關鍵字-妄想.矛盾.自卑.假性遲鈍.怠惰.容易滿足*片刻",
        "id": "1511572100225462281",
        "location": "Iceland",
        "name": "氫氣球",
        "pinned_tweet_id": "1881024842637746685",
        "profile_image_url": "https://pbs.twimg.com/profile_images/1800066723707863040/9h-AfIIc_normal.jpg",
        "protected": false,
        "public_metrics": {
          "followers_count": 2,
          "following_count": 81,
          "like_count": 7619,
          "listed_count": 1,
          "media_count": 26,
          "tweet_count": 585
        },
        "username": "allnightforlive",
        "verified": false
      },
      {
        "created_at": "2022-03-25T16:40:26.000Z",
        "description": "星探小特，诚心帮缺钱的宝子找金主👉： @CalliMauri98320 （有需求的宝子欢迎投稿）",
        "entities": {
          "description": {
            "mentions": [
              {
                "end": 35,
                "start": 19,
                "username": "CalliMauri98320"
              }
            ]
          }
        },
        "id": "1507396901594820608",
        "name": "恋",
        "pinned_tweet_id": "1988913870912598067",
        "profile_image_url": "https://pbs.twimg.com/profile_images/1853640703144046592/OC2mQ87G_normal.jpg",
        "protected": false,
        "public_metrics": {
          "followers_count": 93947,
          "following_count": 2747,
          "like_count": 43342,
          "listed_count": 127,
          "media_count": 3062,
          "tweet_count": 7378
        },
        "username": "hgds0",
        "verified": true
      }
    ]
  }
}