{
  "data": {
    "article": {},
    "attachments": {},
    "author_id": "1511572100225462281",
    "conversation_id": "2046268721749164288",
    "created_at": "2026-04-20T16:44:15.000Z",
    "edit_controls": {
      "editable_until": "2026-04-20T17:44:15.000Z",
      "edits_remaining": 5,
      "is_edit_eligible": true
    },
    "edit_history_tweet_ids": [
      "2046268721749164288"
    ],
    "entities": {},
    "geo": {},
    "id": "2046268721749164288",
    "lang": "zh",
    "note_tweet": {
      "entities": {}
    },
    "possibly_sensitive": false,
    "public_metrics": {
      "bookmark_count": 0,
      "impression_count": 0,
      "like_count": 0,
      "quote_count": 0,
      "reply_count": 0,
      "retweet_count": 0
    },
    "reply_settings": "everyone",
    "text": "好多人都死掉了\n明明自己一點也不在乎的\n明明自己也不混圈子 甚至無法理解死亡對他們而言到底是什麼樣子的\n\n但就是被迫共情\n\n但就是共情到覺得痛苦而麻木\n\n又開始模糊了。"
  },
  "includes": {
    "tweets": [
      {
        "article": {},
        "attachments": {},
        "author_id": "1511572100225462281",
        "conversation_id": "2046268721749164288",
        "created_at": "2026-04-20T16:44:15.000Z",
        "edit_controls": {
          "editable_until": "2026-04-20T17:44:15.000Z",
          "edits_remaining": 5,
          "is_edit_eligible": true
        },
        "edit_history_tweet_ids": [
          "2046268721749164288"
        ],
        "entities": {},
        "geo": {},
        "id": "2046268721749164288",
        "lang": "zh",
        "note_tweet": {
          "entities": {}
        },
        "possibly_sensitive": false,
        "public_metrics": {
          "bookmark_count": 0,
          "impression_count": 0,
          "like_count": 0,
          "quote_count": 0,
          "reply_count": 0,
          "retweet_count": 0
        },
        "reply_settings": "everyone",
        "text": "好多人都死掉了\n明明自己一點也不在乎的\n明明自己也不混圈子 甚至無法理解死亡對他們而言到底是什麼樣子的\n\n但就是被迫共情\n\n但就是共情到覺得痛苦而麻木\n\n又開始模糊了。"
      }
    ],
    "users": [
      {
        "created_at": "2022-04-06T05:11:05.000Z",
        "description": "_未確診的性成癮患者自述 *墮落的自救者**_關鍵字-妄想.矛盾.自卑.淚失禁.假性遲鈍.怠惰.容易滿足*片刻",
        "id": "1511572100225462281",
        "location": "天台",
        "name": "氫氣球",
        "pinned_tweet_id": "1881024842637746685",
        "profile_image_url": "https://pbs.twimg.com/profile_images/1800066723707863040/9h-AfIIc_normal.jpg",
        "protected": false,
        "public_metrics": {
          "followers_count": 19,
          "following_count": 103,
          "like_count": 21295,
          "listed_count": 1,
          "media_count": 52,
          "tweet_count": 1681
        },
        "username": "allnightforlive",
        "verified": false
      }
    ]
  }
}